npsam/__init__.py
npsam/npsam.py
npsam/utils.py
npsam/button_images/Save_close.png
npsam/button_images/Save_close_dark.png
npsam/button_images/arrow.png
npsam/button_images/arrow_dark.png
npsam/button_images/plus_all.png
npsam/button_images/plus_all_dark.png
npsam/button_images/plus_one.png
npsam/button_images/plus_one_dark.png
npsam/segment_anything/__init__.py
npsam/segment_anything/automatic_mask_generator.py
npsam/segment_anything/build_sam.py
npsam/segment_anything/predictor.py
npsam/segment_anything/modeling/__init__.py
npsam/segment_anything/modeling/common.py
npsam/segment_anything/modeling/image_encoder.py
npsam/segment_anything/modeling/mask_decoder.py
npsam/segment_anything/modeling/prompt_encoder.py
npsam/segment_anything/modeling/sam.py
npsam/segment_anything/modeling/transformer.py
npsam/segment_anything/utils/__init__.py
npsam/segment_anything/utils/amg.py
npsam/segment_anything/utils/onnx.py
npsam/segment_anything/utils/transforms.py
npsam-3.2.3.dist-info/licenses/LICENSE.txt
npsam-3.2.3.dist-info/METADATA
npsam-3.2.3.dist-info/WHEEL
npsam-3.2.3.dist-info/top_level.txt
npsam-3.2.3.dist-info/RECORD
