Metadata-Version: 2.4
Name: npsam
Version: 3.2.3
Summary: NP-SAM is an easy-to-use segmentation and analysis tool for nanoparticles and more.
Author-email: "Rohde, R. & Villadsen, T." <rasmus@inano.au.dk>
License-Expression: Apache-2.0
Keywords: nanoparticles,segmentation
Classifier: Development Status :: 4 - Beta
Classifier: Programming Language :: Python
Classifier: Intended Audience :: Science/Research
Requires-Python: >=3.10
License-File: LICENSE.txt
Requires-Dist: numba==0.60.0
Requires-Dist: opencv-python==4.10.0.84
Requires-Dist: pandas==2.2.2
Requires-Dist: matplotlib==3.8.2
Requires-Dist: scikit-image==0.24.0
Requires-Dist: ipympl==0.9.4
Requires-Dist: PyQt6==6.7.0
Requires-Dist: ultralytics==8.3.27
Requires-Dist: jupyterlab==4.2.2
Requires-Dist: clip==0.2.0
Requires-Dist: hyperspy[all]==2.1.1
Requires-Dist: exspy==0.2
Requires-Dist: rosettasciio==0.6
Requires-Dist: parse==1.20.2
Requires-Dist: sparse==0.15.4
Requires-Dist: tifffile==2024.6.18
Requires-Dist: matplotlib_scalebar==0.9.0
Dynamic: license-file
